main_script.py
main_script-0.1.0.dist-info/WHEEL
main_script-0.1.0.dist-info/METADATA
main_script-0.1.0.dist-info/RECORD
