Metadata-Version: 2.1
Name: main-script
Version: 0.1.0
Summary: A simple decorator to replace if __name__ == '__main__' with @main_script
Home-page: UNKNOWN
License: UNKNOWN
Author: Matt Kramer
Author-email: matthew.robert.kramer@gmail.com
Requires-Python: >=3.7,<4.0
Classifier: Programming Language :: Python :: 3
Classifier: Programming Language :: Python :: 3.7
